weather_43538932325/__init__.py
weather_43538932325-0.1.0.dist-info/WHEEL
weather_43538932325-0.1.0.dist-info/entry_points.txt
weather_43538932325-0.1.0.dist-info/METADATA
weather_43538932325-0.1.0.dist-info/RECORD
